{"stat.killEntity.EntityHorse":1,"stat.leaveGame":162,"stat.mineBlock.139":60,"stat.killEntity.PigZombie":89,"stat.entityKilledBy.PigZombie":1,"stat.mineBlock.145":13,"achievement.diamondsToYou":1,"stat.mineBlock.110":2,"stat.mineBlock.111":56,"stat.mineBlock.114":3,"achievement.botania:flowerPickup":142,"stat.killEntity.Enderman":49,"stat.mineBlock.112":12,"stat.mineBlock.113":4,"stat.mineBlock.116":13,"achievement.buildPickaxe":20,"metAttractedDrop":16,"stat.killEntity.Witch":13,"stat.killEntity.Villager":4,"stat.mineBlock.121":26,"stat.mineBlock.126":3,"stat.mineBlock.129":22,"stat.mineBlock.127":8,"stat.killEntity.CometKitty":3,"ic2.acquireResin":4,"stat.mineBlock.175":16,"tconstruct.beginner":3,"stat.entityKilledBy.witherSkeleton":1,"achievement.openInventory":9744,"stat.mineBlock.161":17,"stat.mineBlock.154":4,"stat.mineBlock.152":1,"stat.mineBlock.153":738,"stat.mineBlock.159":32,"stat.deaths":105,"stat.mineBlock.170":178,"stat.mineBlock.171":22,"achievement.potion":11,"stat.killEntity.Ghast":10,"achievement.killCow":66,"achievement.bakeCake":3,"achievement.enterAether":13580,"achievement.botania:lexiconUse":26,"achievement.portal":4,"stat.entityKilledBy.Wolf":1,"stat.useItem.6":110,"achievement.acquireIron":20,"stat.useItem.1":85,"stat.useItem.4":1089,"stat.useItem.5":86,"stat.useItem.3":2074,"draconicevolution.dust":290,"stat.useItem.351":1228,"stat.craftItem.69":8,"stat.useItem.355":5,"stat.useItem.113":1,"stat.useItem.354":1,"stat.useItem.356":3,"stat.useItem.359":522,"stat.useItem.116":1,"stat.craftItem.61":3,"stat.craftItem.67":4,"stat.craftItem.65":27,"stat.useItem.362":4,"stat.useItem.361":18,"stat.useItem.121":1,"stat.useItem.126":5,"tconstruct.pattern":16,"stat.useItem.129":3,"achievement.buildWorkBench":20,"stat.craftItem.76":1,"stat.craftItem.77":5,"stat.craftItem.70":1,"achievement.ae2.ChargedQuartz":88,"stat.useItem.331":26,"stat.useItem.330":5,"stat.craftItem.85":34,"stat.useItem.338":62,"stat.craftItem.89":191,"stat.mineBlock.4":288,"stat.mineBlock.5":86,"stat.mineBlock.3":1627,"stat.mineBlock.1":7679,"stat.craftItem.82":381,"stat.craftItem.80":16,"stat.mineBlock.6":6,"stat.flyOneCm":34902566,"stat.useItem.102":27,"stat.useItem.101":21,"stat.useItem.106":14,"stat.craftItem.96":4,"stat.useItem.107":5,"stat.craftItem.95":0,"stat.craftItem.98":4,"stat.craftItem.91":2,"ic2.mineOre":5524,"stat.craftItem.25":2,"stat.killEntity.Bat":1,"stat.breakItem.292":1,"stat.breakItem.291":2,"stat.craftItem.420":2,"stat.craftItem.20":58,"stat.killEntity.Wolf":1,"stat.killEntity.Creeper":47,"stat.ae2.ItemsInserted":57809,"stat.useItem.321":2,"stat.useItem.324":6,"stat.useItem.323":5,"stat.craftItem.35":37,"stat.entityKilledBy.Skeleton":5,"stat.craftItem.33":2,"achievement.buildSword":8,"stat.killEntity.Squid":5,"stat.killEntity.GalacticraftCore.EvolvedSkeleton":13,"stat.breakItem.270":1,"stat.breakItem.272":2,"stat.breakItem.274":2,"stat.breakItem.273":1,"stat.craftItem.42":1,"stat.breakItem.275":1,"stat.breakItem.278":4,"stat.craftItem.45":2,"stat.craftItem.44":36,"stat.breakItem.279":1,"achievement.killEnemy":2117,"stat.craftItem.58":16,"stat.killEntity.GalacticraftMars.Slimeling":2,"stat.craftItem.50":252,"stat.breakItem.267":1,"stat.craftItem.57":9,"stat.craftItem.54":34,"stat.killEntity.Zombie":560,"stat.diveOneCm":558287,"stat.useItem.65":20,"stat.useItem.66":1,"stat.useItem.61":8,"achievement.buildHoe":5,"stat.breakItem.258":7,"stat.breakItem.257":3,"stat.useItem.69":3,"stat.useItem.76":2,"stat.entityKilledBy.Pig":1,"stat.craftItem.296":18,"stat.useItem.77":2,"stat.jump":24767,"stat.useItem.73":14,"stat.craftItem.291":3,"achievement.hee.3548":1,"stat.useItem.44":55,"achievement.blazeRod":14,"stat.damageTaken":447307,"achievement.cfm_install":164,"stat.useItem.47":3,"stat.useItem.48":6,"stat.useItem.49":1,"stat.useItem.54":85,"stat.useItem.56":13,"stat.useItem.50":522,"tconstruct.tinkerer":1,"stat.entityKilledBy.Zombie":37,"stat.useItem.58":15,"stat.useItem.153":2,"stat.useItem.152":2,"stat.useItem.21":3,"stat.craftItem.263":120,"stat.useItem.397":152,"stat.useItem.22":16,"stat.craftItem.264":1715,"stat.craftItem.265":443,"stat.craftItem.266":22,"stat.craftItem.267":1,"stat.animalsBred":21,"stat.craftItem.268":1,"stat.craftItem.259":4,"stat.useItem.31":15,"stat.useItem.33":1,"stat.craftItem.256":1,"stat.craftItem.257":3,"stat.useItem.30":3,"metMaterialGather":223,"stat.useItem.39":1,"stat.useItem.35":10,"stat.useItem.171":329,"stat.useItem.170":5,"stat.useItem.37":3,"stat.useItem.38":17,"stat.useItem.130":2,"stat.useItem.372":41,"stat.craftItem.284":0,"stat.useItem.379":3,"stat.useItem.139":153,"stat.craftItem.280":628,"stat.mobKills":2465,"stat.useItem.380":3,"stat.craftItem.272":3,"stat.useItem.383":2,"stat.craftItem.274":3,"stat.useItem.12":80,"stat.craftItem.275":2,"stat.craftItem.276":1,"stat.useItem.146":2,"stat.craftItem.277":1,"stat.craftItem.278":6,"stat.craftItem.279":1,"stat.craftItem.270":2,"stat.useItem.17":20,"stat.useItem.391":15,"stat.useItem.13":138,"stat.useItem.390":1,"stat.useItem.14":2,"stat.useItem.15":41,"stat.useItem.392":39,"stat.killEntity.Blaze":5,"stat.mineBlock.14":186,"stat.mineBlock.13":242,"stat.mineBlock.16":1513,"stat.mineBlock.15":580,"stat.mineBlock.18":6450,"stat.mineBlock.17":941,"stat.mineBlock.12":21,"achievement.diamonds":337,"achievement.buildBetterPickaxe":18,"achievement.breedCow":1,"stat.killEntity.witherSkeleton":56,"achievement.mineWood":838,"stat.useItem.86":3,"stat.useItem.87":13,"stat.useItem.88":126,"stat.useItem.89":14,"stat.useItem.82":76,"stat.useItem.84":1,"stat.useItem.85":69,"stat.useItem.81":52,"stat.useItem.98":11,"stat.playOneMinute":9051428,"stat.killEntity.Battletower Golem":43,"stat.fallOneCm":81866,"stat.craftItem.1":22,"draconicevolution.soul":6,"stat.craftItem.5":488,"stat.entityKilledBy.Battletower Golem":3,"stat.killEntity.GalacticraftCore.EvolvedZombie":3,"stat.blockChiseled":5380,"stat.killEntity.GalacticraftCore.EvolvedCreeper":7,"stat.craftItem.340":0,"stat.craftItem.101":16,"stat.craftItem.102":64,"stat.horseOneCm":5799,"stat.craftItem.336":88,"stat.craftItem.339":273,"stat.craftItem.331":2265,"stat.swimOneCm":314236,"stat.craftItem.333":0,"achievement.botania:cacophoniumCraft":1,"stat.climbOneCm":216455,"stat.ae2.ItemsExtracted":39601,"stat.craftItem.324":0,"stat.craftItem.325":1,"achievement.exploreAllBiomes":{"value":0,"progress":["Sky","Desert M","Birch Forest","Roofed Forest","Extreme Hills M","Tainted Land","Redwood Forest","Desert Oil Field","Extreme Hills+ M","Beach","Taiga","Mega Taiga","Green Hills","Meadow","Roofed Forest M","ForestHills","Lush Redwoods","Plains","Pine Forest","TaigaHills","Enchanted Forest","moon","Stone Beach","Eerie","Temperate Rainforest","Red Rock Mountains","Shrubland","Swampland M","Savanna","Sunflower Plains","Mountain Taiga","Woodlands","Forested Island","Mountainous Desert","Autumn Woods","Rainforest","FrozenRiver","Mega Taiga Hills","Aether","Extreme Hills+","River","Ocean","Swampland","Extreme Jungle","Magical Forest","Flower Forest","DesertHills","marsFlat","Ice Plains","Mini Jungle","Forest","Forested Hills","Green Swamplands","Desert","Extreme Hills","Tundra","Deep Ocean","Hell"]},"achievement.botania:daybloomPickup":4,"stat.craftItem.361":20,"stat.craftItem.362":4,"stat.craftItem.364":15,"stat.craftItem.359":4,"stat.killEntity.GalacticraftCore.EvolvedSpider":11,"stat.craftItem.350":21,"stat.craftItem.351":1096,"stat.craftItem.353":20,"stat.craftItem.354":3,"stat.craftItem.346":1,"stat.craftItem.347":0,"stat.killEntity.Blizz":9,"stat.craftItem.107":2,"stat.craftItem.109":0,"ic2.acquireRefinedIron":19,"stat.killEntity.Blitz":7,"stat.craftItem.320":103,"stat.craftItem.314":11,"stat.craftItem.315":8,"stat.craftItem.316":11,"stat.craftItem.317":3,"stat.entityKilledBy.Creeper":1,"achievement.buildFurnace":3,"stat.drop":6163,"stat.useItem.420":11,"stat.killEntity.Sheep":2,"stat.craftItem.303":1,"stat.mineBlock.81":39,"stat.mineBlock.82":78,"stat.mineBlock.85":37,"stat.mineBlock.87":142,"stat.mineBlock.86":89,"stat.mineBlock.89":44,"stat.mineBlock.88":13,"stat.craftItem.170":8,"stat.craftItem.171":285,"stat.breakItem.359":2,"stat.entityKilledBy.CaveSpider":2,"stat.mineBlock.98":224,"stat.mineBlock.99":22,"stat.mineBlock.69":2,"stat.useItem.295":154,"stat.mineBlock.61":8,"stat.mineBlock.65":20,"stat.mineBlock.67":14,"stat.mineBlock.66":16,"stat.killEntity.CaveSpider":83,"stat.mineBlock.79":7,"stat.damageDealt":122631,"stat.mineBlock.70":1,"stat.killEntity.Cow":11,"stat.mineBlock.73":194,"stat.killEntity.Pig":25,"stat.mineBlock.76":7,"stat.useItem.274":356,"stat.mineBlock.47":80,"stat.craftItem.382":0,"stat.useItem.273":137,"stat.useItem.276":668,"stat.mineBlock.49":30,"stat.mineBlock.48":77,"stat.useItem.275":93,"stat.craftItem.143":1,"stat.walkOneCm":27591800,"stat.useItem.278":16071,"stat.useItem.277":538,"stat.craftItem.146":1,"stat.craftItem.389":6,"stat.useItem.279":245,"stat.craftItem.381":2,"stat.craftItem.379":0,"stat.mineBlock.44":182,"stat.mineBlock.58":11,"stat.craftItem.371":81,"stat.craftItem.130":0,"stat.useItem.287":83,"stat.craftItem.131":0,"stat.craftItem.374":66,"stat.craftItem.133":32,"stat.craftItem.376":2,"stat.craftItem.377":2,"stat.craftItem.378":0,"stat.breakItem.317":1,"stat.breakItem.316":1,"stat.mineBlock.103":14,"stat.mineBlock.101":86,"stat.mineBlock.102":25,"stat.mineBlock.50":157,"stat.craftItem.126":30,"stat.mineBlock.107":3,"stat.killEntity.Basalz":6,"stat.mineBlock.106":200,"stat.useItem.292":321,"stat.mineBlock.54":46,"stat.useItem.291":341,"stat.mineBlock.56":23,"stat.mineBlock.109":19,"stat.mineBlock.24":3,"stat.killEntity.Skeleton":219,"stat.useItem.256":84,"stat.useItem.258":832,"stat.useItem.257":690,"stat.useItem.259":33,"stat.killEntity.Chicken":10,"stat.craftItem.160":0,"stat.killEntity.Spider":171,"stat.breakItem.306":1,"stat.breakItem.308":1,"stat.breakItem.307":2,"stat.breakItem.309":1,"stat.mineBlock.21":17,"stat.mineBlock.20":1,"stat.mineBlock.23":5,"stat.mineBlock.22":16,"stat.craftItem.393":6,"stat.mineBlock.35":20,"stat.craftItem.152":926,"stat.mineBlock.38":85,"stat.mineBlock.37":144,"stat.craftItem.396":4,"stat.useItem.267":267,"stat.craftItem.155":0,"stat.mineBlock.39":3,"stat.useItem.268":10,"stat.craftItem.148":1,"stat.mineBlock.30":55,"achievement.cookFish":24,"stat.useItem.270":72,"stat.mineBlock.31":920,"stat.useItem.272":358,"stat.mineBlock.33":45}