{"stat.leaveGame":120,"stat.mineBlock.13":72,"stat.mineBlock.16":51,"stat.mineBlock.15":7,"stat.mineBlock.18":4744,"stat.mineBlock.17":1128,"stat.mineBlock.12":278,"stat.entityKilledBy.Basalz":1,"achievement.botania:flowerPickup":3,"achievement.buildPickaxe":7,"achievement.buildBetterPickaxe":7,"stat.mineBlock.126":14,"tconstruct.beginner":1,"achievement.blueCloud":6,"achievement.mineWood":820,"stat.useItem.89":70,"stat.useItem.85":236,"achievement.openInventory":2210,"stat.useItem.81":6,"stat.mineBlock.154":5,"stat.useItem.98":7,"stat.deaths":40,"stat.useItem.96":2,"stat.playOneMinute":5622236,"stat.useItem.90":20,"stat.killEntity.Battletower Golem":4,"stat.fallOneCm":1737766,"stat.useItem.404":9,"stat.craftItem.1":121,"stat.craftItem.5":1529,"achievement.enterAether":9181,"achievement.companion":37,"stat.blockChiseled":154,"stat.entityKilledBy.Enderman":1,"stat.useItem.8":6,"stat.useItem.7":37,"stat.useItem.1":3139,"stat.useItem.4":1900,"stat.useItem.5":735,"stat.useItem.3":10848,"draconicevolution.dust":52,"stat.useItem.351":15,"stat.useItem.355":3,"stat.craftItem.101":32,"stat.craftItem.102":112,"stat.useItem.356":18,"stat.craftItem.61":6,"stat.craftItem.67":152,"stat.craftItem.331":199,"stat.swimOneCm":861035,"stat.useItem.126":45,"stat.climbOneCm":62721,"stat.craftItem.72":3,"stat.craftItem.76":15,"achievement.buildWorkBench":7,"stat.ae2.ItemsExtracted":21,"stat.craftItem.324":4,"stat.craftItem.325":3,"achievement.exploreAllBiomes":{"value":0,"progress":["Sky","Sunflower Plains","Mountain Taiga","Birch Forest","Roofed Forest","Rainforest","Extreme Hills+ M","Beach","Aether","Extreme Hills+","River","Ocean","Taiga","Green Hills","Extreme Jungle","Meadow","ForestHills","Magical Forest","Flower Forest","Plains","Enchanted Forest","Stone Beach","Eerie","Forest","Shrubland","Extreme Hills","Tundra","Deep Ocean","Hell"]},"stat.useItem.331":64,"stat.craftItem.85":232,"stat.useItem.338":979,"stat.mineBlock.4":568,"stat.mineBlock.5":399,"stat.mineBlock.3":6168,"stat.mineBlock.1":1206,"stat.flyOneCm":25506657,"stat.craftItem.351":15,"stat.useItem.102":176,"stat.craftItem.355":2,"stat.craftItem.356":3,"ic2.mineOre":219,"stat.craftItem.20":465,"stat.killEntity.Creeper":1,"stat.useItem.324":9,"stat.useItem.323":8,"stat.entityKilledBy.Skeleton":4,"stat.craftItem.33":2,"stat.craftItem.404":2,"stat.craftItem.406":2,"stat.craftItem.322":10,"stat.craftItem.41":3,"stat.breakItem.274":2,"stat.breakItem.273":6,"stat.breakItem.275":2,"stat.breakItem.277":1,"stat.craftItem.44":84,"stat.entityKilledBy.Creeper":2,"achievement.buildFurnace":6,"stat.craftItem.58":4,"stat.drop":1334,"stat.craftItem.53":60,"stat.craftItem.57":9,"stat.craftItem.54":21,"stat.killEntity.Zombie":37,"stat.diveOneCm":653551,"stat.useItem.67":12,"achievement.buildHoe":1,"stat.breakItem.256":3,"stat.breakItem.257":2,"stat.mineBlock.81":8,"stat.mineBlock.82":41,"stat.mineBlock.85":43,"stat.mineBlock.89":25,"stat.useItem.76":48,"stat.useItem.72":4,"stat.jump":29367,"stat.craftItem.290":0,"stat.craftItem.293":1,"achievement.hee.3548":1,"stat.mineBlock.98":7,"stat.mineBlock.99":136,"stat.useItem.295":287,"stat.useItem.44":3,"stat.damageTaken":553723,"achievement.cfm_install":124,"stat.useItem.48":20,"stat.useItem.49":51,"stat.useItem.53":79,"stat.useItem.54":21,"stat.mineBlock.79":6150,"stat.killEntity.CaveSpider":25,"stat.useItem.50":35,"stat.entityKilledBy.Zombie":12,"stat.damageDealt":31012,"stat.mineBlock.72":1,"stat.killEntity.Pig":1,"stat.mineBlock.73":3,"stat.mineBlock.76":47,"stat.useItem.57":3,"stat.useItem.58":2,"stat.mineBlock.78":133,"stat.useItem.20":32,"stat.useItem.274":361,"stat.useItem.273":727,"stat.mineBlock.49":11,"stat.useItem.276":93,"stat.useItem.154":5,"stat.mineBlock.48":145,"stat.useItem.275":177,"stat.craftItem.264":14,"stat.walkOneCm":12040808,"stat.useItem.278":1866,"stat.craftItem.265":189,"stat.useItem.277":3062,"stat.craftItem.266":43,"stat.playerKills":4,"stat.useItem.279":1009,"stat.craftItem.380":2,"stat.useItem.24":12,"stat.mineBlock.44":2,"stat.mineBlock.58":2,"stat.craftItem.371":27,"stat.craftItem.130":1,"stat.craftItem.256":3,"stat.craftItem.257":5,"stat.mineBlock.100":59,"stat.mineBlock.102":41,"stat.mineBlock.50":129,"stat.craftItem.126":126,"stat.useItem.290":40,"stat.mineBlock.54":14,"stat.useItem.292":152,"stat.mineBlock.53":39,"stat.useItem.293":809,"stat.mineBlock.24":6,"stat.killEntity.Skeleton":84,"stat.useItem.256":1333,"stat.useItem.257":1051,"stat.useItem.259":31,"stat.killEntity.Chicken":1,"stat.craftItem.280":660,"stat.killEntity.Spider":17,"stat.mobKills":195,"stat.mineBlock.20":11,"stat.craftItem.152":5,"stat.craftItem.273":4,"stat.craftItem.274":2,"stat.mineBlock.38":1,"stat.useItem.12":2047,"stat.craftItem.154":1,"stat.craftItem.275":1,"stat.mineBlock.37":1,"stat.useItem.267":26,"stat.mineBlock.39":4,"stat.craftItem.277":2,"stat.craftItem.278":8,"stat.craftItem.271":1,"stat.useItem.17":625,"stat.mineBlock.30":38,"stat.useItem.13":58,"stat.mineBlock.31":24,"stat.useItem.272":90}